sales_report/__init__.py
sales_report/cli.py
sales_report/report_generator.py
sales_report12-0.1.8.dist-info/METADATA
sales_report12-0.1.8.dist-info/WHEEL
sales_report12-0.1.8.dist-info/entry_points.txt
sales_report12-0.1.8.dist-info/top_level.txt
sales_report12-0.1.8.dist-info/RECORD
